modernrpc/__init__.py
modernrpc/apps.py
modernrpc/auth.py
modernrpc/compat.py
modernrpc/config/__init__.py
modernrpc/config/default_settings.py
modernrpc/constants.py
modernrpc/core.py
modernrpc/exceptions.py
modernrpc/handler.py
modernrpc/helpers.py
modernrpc/introspection.py
modernrpc/jsonrpc/backends/__init__.py
modernrpc/jsonrpc/backends/json.py
modernrpc/jsonrpc/backends/marshalling.py
modernrpc/jsonrpc/backends/orjson.py
modernrpc/jsonrpc/backends/rapidjson.py
modernrpc/jsonrpc/backends/simplejson.py
modernrpc/jsonrpc/handler.py
modernrpc/server.py
modernrpc/system_procedures.py
modernrpc/types.py
modernrpc/views.py
modernrpc/xmlrpc/backends/__init__.py
modernrpc/xmlrpc/backends/constants.py
modernrpc/xmlrpc/backends/etree.py
modernrpc/xmlrpc/backends/lxml.py
modernrpc/xmlrpc/backends/marshalling.py
modernrpc/xmlrpc/backends/xmlrpc.py
modernrpc/xmlrpc/backends/xmltodict.py
modernrpc/xmlrpc/handler.py
django_modern_rpc-2.0.0.dist-info/licenses/LICENSE.txt
django_modern_rpc-2.0.0.dist-info/WHEEL
django_modern_rpc-2.0.0.dist-info/METADATA
django_modern_rpc-2.0.0.dist-info/RECORD
