Metadata-Version: 2.4
Name: django-modern-rpc
Version: 2.0.0
Summary: Simple and powerful RPC server for your Django project
Author: Antoine Lorence
Author-email: Antoine Lorence <antoine.lorence@gmail.com>
License-Expression: MIT
License-File: LICENSE.txt
Classifier: Programming Language :: Python
Classifier: Development Status :: 5 - Production/Stable
Classifier: Environment :: Web Environment
Classifier: License :: OSI Approved :: MIT License
Classifier: Operating System :: OS Independent
Classifier: Programming Language :: Python :: 3
Classifier: Programming Language :: Python :: 3.8
Classifier: Programming Language :: Python :: 3.9
Classifier: Programming Language :: Python :: 3.10
Classifier: Programming Language :: Python :: 3.11
Classifier: Programming Language :: Python :: 3.12
Classifier: Programming Language :: Python :: 3.13
Classifier: Programming Language :: Python :: 3.14
Classifier: Framework :: Django
Classifier: Framework :: Django :: 3.2
Classifier: Framework :: Django :: 4.0
Classifier: Framework :: Django :: 4.1
Classifier: Framework :: Django :: 4.2
Classifier: Framework :: Django :: 5.0
Classifier: Framework :: Django :: 5.1
Classifier: Framework :: Django :: 5.2
Classifier: Framework :: Django :: 6.0
Classifier: Intended Audience :: Developers
Classifier: Topic :: Software Development :: Libraries :: Python Modules
Classifier: Topic :: Internet :: WWW/HTTP :: HTTP Servers
Requires-Dist: django>=3.2
Requires-Dist: defusedxml>=0.7.1
Requires-Dist: typing-extensions>=4.12.0 ; python_full_version < '3.11'
Requires-Dist: docutils ; extra == 'docutils'
Requires-Dist: lxml ; extra == 'lxml'
Requires-Dist: markdown ; extra == 'markdown'
Requires-Dist: orjson ; extra == 'orjson'
Requires-Dist: python-rapidjson ; extra == 'rapidjson'
Requires-Dist: simplejson ; extra == 'simplejson'
Requires-Dist: xmltodict ; extra == 'xmltodict'
Requires-Python: >=3.8
Project-URL: Bug Tracker, https://github.com/alorence/django-modern-rpc/issues
Project-URL: Demo, https://modernrpc.fly.dev
Provides-Extra: docutils
Provides-Extra: lxml
Provides-Extra: markdown
Provides-Extra: orjson
Provides-Extra: rapidjson
Provides-Extra: simplejson
Provides-Extra: xmltodict
